rstms_vimfix/__init__.py
rstms_vimfix/cli.py
rstms_vimfix/exception_handler.py
rstms_vimfix/shell.py
rstms_vimfix/verify.py
rstms_vimfix/version.py
rstms_vimfix/vimfix.py
rstms_vimfix-0.1.17.dist-info/entry_points.txt
rstms_vimfix-0.1.17.dist-info/LICENSE
rstms_vimfix-0.1.17.dist-info/WHEEL
rstms_vimfix-0.1.17.dist-info/METADATA
rstms_vimfix-0.1.17.dist-info/RECORD
